tubeup_ac/TubeUp.py
tubeup_ac/__init__.py
tubeup_ac/__main__.py
tubeup_ac/utils.py
tubeup_ac-2024.6.28.dist-info/LICENSE
tubeup_ac-2024.6.28.dist-info/METADATA
tubeup_ac-2024.6.28.dist-info/WHEEL
tubeup_ac-2024.6.28.dist-info/entry_points.txt
tubeup_ac-2024.6.28.dist-info/top_level.txt
tubeup_ac-2024.6.28.dist-info/RECORD
